stache_ai_redis/__init__.py
stache_ai_redis/provider.py
stache_ai_redis-0.1.0.dist-info/METADATA
stache_ai_redis-0.1.0.dist-info/WHEEL
stache_ai_redis-0.1.0.dist-info/entry_points.txt
stache_ai_redis-0.1.0.dist-info/top_level.txt
stache_ai_redis-0.1.0.dist-info/RECORD
