Metadata-Version: 2.4
Name: stache-ai-redis
Version: 0.1.0
Summary: Redis provider for Stache AI
Author: Stache Contributors
License: MIT
Project-URL: Homepage, https://github.com/stache-ai/stache-ai
Project-URL: Repository, https://github.com/stache-ai/stache-ai
Keywords: stache,rag,ai,redis
Classifier: Development Status :: 4 - Beta
Classifier: Intended Audience :: Developers
Classifier: License :: OSI Approved :: MIT License
Classifier: Programming Language :: Python :: 3
Classifier: Programming Language :: Python :: 3.10
Classifier: Programming Language :: Python :: 3.11
Classifier: Programming Language :: Python :: 3.12
Requires-Python: >=3.10
Requires-Dist: stache-ai<1.0.0,>=0.1.0
Requires-Dist: redis>=5.0.0
Provides-Extra: dev
Requires-Dist: pytest>=7.0.0; extra == "dev"
Requires-Dist: pytest-asyncio>=0.21.0; extra == "dev"
Requires-Dist: pytest-cov>=4.0.0; extra == "dev"
